axiom_sqlalchemy/__init__.py
axiom_sqlalchemy/controller/__init__.py
axiom_sqlalchemy/controller/sqlalchemy.py
axiom_sqlalchemy/database/__init__.py
axiom_sqlalchemy/database/session.py
axiom_sqlalchemy/database/postgres/__init__.py
axiom_sqlalchemy/database/postgres/base.py
axiom_sqlalchemy/database/postgres/meta.py
axiom_sqlalchemy/database/postgres/session.py
axiom_sqlalchemy/database/postgres/dependency/__init__.py
axiom_sqlalchemy/database/postgres/dependency/session.py
axiom_sqlalchemy/database/postgres/mixin/__init__.py
axiom_sqlalchemy/database/postgres/mixin/as_dict.py
axiom_sqlalchemy/database/postgres/mixin/timestamp.py
axiom_sqlalchemy/exception/__init__.py
axiom_sqlalchemy/exception/database.py
axiom_sqlalchemy/repository/__init__.py
axiom_sqlalchemy/repository/sqlalchemy.py
axiom_sqlalchemy-0.1.2.dist-info/METADATA
axiom_sqlalchemy-0.1.2.dist-info/WHEEL
axiom_sqlalchemy-0.1.2.dist-info/RECORD
