Metadata-Version: 2.4
Name: axiom-sqlalchemy
Version: 0.1.2
Summary: Add your description here
Project-URL: Repository, https://github.com/Kamaliev/axiom-sqlalchemy
Author: Kamaliev
License: MIT
Classifier: Operating System :: OS Independent
Classifier: Programming Language :: Python :: 3
Requires-Python: >=3.13
Requires-Dist: asyncpg>=0.31.0
Requires-Dist: axiom-core>=0.1.2
Requires-Dist: sqlalchemy>=2.0.45
